row_estimator_for_apache_cassandra/__init__.py
row_estimator_for_apache_cassandra/__main__.py
row_estimator_for_apache_cassandra/estimator.py
row_estimator_for_apache_cassandra-0.0.3.dist-info/LICENSE
row_estimator_for_apache_cassandra-0.0.3.dist-info/METADATA
row_estimator_for_apache_cassandra-0.0.3.dist-info/NOTICE.txt
row_estimator_for_apache_cassandra-0.0.3.dist-info/WHEEL
row_estimator_for_apache_cassandra-0.0.3.dist-info/entry_points.txt
row_estimator_for_apache_cassandra-0.0.3.dist-info/top_level.txt
row_estimator_for_apache_cassandra-0.0.3.dist-info/RECORD
