Metadata-Version: 2.1
Name: row-estimator-for-apache-cassandra
Version: 0.0.3
Summary: The Row Estimator for Apache Cassandra gathers row level statistics from a Cassandra cluster to help determine roughly a single Cassandra row in bytes to estimate
Home-page: https://github.com/aws-samples/row-estimator-for-apache-cassandra
Author: kolesnn
Author-email: kolesnn@amazon.com
License: Apache License 2.0
Download-URL: https://github.com/aws-samples/row-estimator-for-apache-cassandra/row_estimator_for_apache_cassandra-v0.1.tgz
Keywords: row_estimator_for_apache_cassandra ApacheCassandra AmazonKeyspaces
Platform: UNKNOWN
Classifier: Development Status :: 5 - Production/Stable
Classifier: Topic :: Utilities
Classifier: License :: OSI Approved :: Apache Software License
Requires-Python: >=3.6
Requires-Dist: cassandra-driver
